ssltest/Args.py
ssltest/ConfigSetup.py
ssltest/__init__.py
ssltest/__main__.py
ssltest/logging.py
ssltest/configs/cipher_parameters.json
ssltest/configs/cipher_suites.json
ssltest/configs/cipher_suites_sslv2.json
ssltest/configs/english_strings.json
ssltest/configs/network_profile_usage.json
ssltest/configs/network_profiles.json
ssltest/configs/security_levels.json
ssltest/core/Script.py
ssltest/core/__init__.py
ssltest/core/run.py
ssltest/core/scan.py
ssltest/core/utils.py
ssltest/network/ClientHello.py
ssltest/network/Endpoint.py
ssltest/network/SSLv2.py
ssltest/network/SSLv3.py
ssltest/network/SSLvN.py
ssltest/network/__init__.py
ssltest/output/TextOutput.py
ssltest/output/__init__.py
ssltest/parameters/__init__.py
ssltest/parameters/ratable/Certificate.py
ssltest/parameters/ratable/CipherSuite.py
ssltest/parameters/ratable/CipherSuites.py
ssltest/parameters/ratable/PType.py
ssltest/parameters/ratable/Parameters.py
ssltest/parameters/ratable/ProtocolSupport.py
ssltest/parameters/ratable/__init__.py
ssltest/parameters/unratable/WebServerSoft.py
ssltest/parameters/unratable/__init__.py
ssltest/parameters/unratable/port_discovery.py
ssltest/sockets/ProfileParser.py
ssltest/sockets/SafeSocket.py
ssltest/sockets/SecureSafeSocket.py
ssltest/sockets/SocketAddress.py
ssltest/sockets/__init__.py
ssltest/vulnerabilities/CipherSuiteTest.py
ssltest/vulnerabilities/TestRunner.py
ssltest/vulnerabilities/VulnerabilityTest.py
ssltest/vulnerabilities/__init__.py
ssltest/vulnerabilities/tests/Breach.py
ssltest/vulnerabilities/tests/CCSInjection.py
ssltest/vulnerabilities/tests/Crime.py
ssltest/vulnerabilities/tests/Drown.py
ssltest/vulnerabilities/tests/FallbackSCSVSupport.py
ssltest/vulnerabilities/tests/ForwardSecrecySupport.py
ssltest/vulnerabilities/tests/Freak.py
ssltest/vulnerabilities/tests/HSTSSupport.py
ssltest/vulnerabilities/tests/Heartbleed.py
ssltest/vulnerabilities/tests/InsecureRenegotiation.py
ssltest/vulnerabilities/tests/Logjam.py
ssltest-0.2.2.dist-info/LICENSE
ssltest-0.2.2.dist-info/METADATA
ssltest-0.2.2.dist-info/WHEEL
ssltest-0.2.2.dist-info/entry_points.txt
ssltest-0.2.2.dist-info/top_level.txt
ssltest-0.2.2.dist-info/RECORD
