Metadata-Version: 2.1
Name: ssltest
Version: 0.2.2
Summary: Scan web servers cryptographic parameters and vulnerabilities
Home-page: https://www.penterep.io/
Author: Samuel Kopecky
Author-email: samo.kopecky@protonmail.com
License: GPLv3
Project-URL: Source, https://github.com/SamoKopecky/ssltest
Project-URL: Documentation, https://ssltest.readthedocs.io/en/latest
Classifier: License :: OSI Approved :: GNU General Public License v3 (GPLv3)
Classifier: Programming Language :: Python :: 3.6
Classifier: Environment :: Console
Requires-Python: >=3.6
License-File: LICENSE
Requires-Dist: ptlibs
Requires-Dist: cryptography
Requires-Dist: pyOpenSSL
Requires-Dist: python3-nmap
Requires-Dist: requests
Requires-Dist: urllib3
